festo_python_logging/__init__.py
festo_python_logging/formatter.py
festo_python_logging/test.py
festo_python_logging-0.0.9.dist-info/METADATA
festo_python_logging-0.0.9.dist-info/WHEEL
festo_python_logging-0.0.9.dist-info/RECORD
