Metadata-Version: 2.4
Name: festo-python-logging
Version: 0.0.9
Summary: Convenience function to configure python logging.
License: Proprietary
Author: Charles Wilmot
Author-email: charles.wilmot@festo.com
Maintainer: Charles Wilmot
Maintainer-email: charles.wilmot@festo.com
Requires-Python: >=3.10
Classifier: License :: Other/Proprietary License
Classifier: Programming Language :: Python :: 3
Classifier: Programming Language :: Python :: 3.10
Classifier: Programming Language :: Python :: 3.11
Classifier: Programming Language :: Python :: 3.12
Classifier: Programming Language :: Python :: 3.13
Classifier: Programming Language :: Python :: 3.14
